pymaft/__init__.py
pymaft/dms.cpython-37m-darwin.so
pymaft/solvers.cpython-37m-darwin.so
pymaft/utils.cpython-37m-darwin.so
pymaft-1.0.1.dist-info/LICENSE
pymaft-1.0.1.dist-info/METADATA
pymaft-1.0.1.dist-info/WHEEL
pymaft-1.0.1.dist-info/top_level.txt
pymaft-1.0.1.dist-info/RECORD
